local_qwen3b_part011/__init__.py
local_qwen3b_part011/qwen2.5-3b-instruct-q5_k_m.gguf.part_011
local_qwen3b_part011-0.0.1.dist-info/METADATA
local_qwen3b_part011-0.0.1.dist-info/WHEEL
local_qwen3b_part011-0.0.1.dist-info/top_level.txt
local_qwen3b_part011-0.0.1.dist-info/RECORD
